snapvision/__init__.py
snapvision/capture.py
snapvision/cli.py
snapvision/config.py
snapvision/hotkeys.py
snapvision/llm.py
snapvision/ocr.py
snapvision/utils.py
snapvision/vision.py
snapvision/ui/__init__.py
snapvision/ui/popup.py
snapvision-0.1.0.dist-info/METADATA
snapvision-0.1.0.dist-info/WHEEL
snapvision-0.1.0.dist-info/entry_points.txt
snapvision-0.1.0.dist-info/top_level.txt
snapvision-0.1.0.dist-info/RECORD
