Metadata-Version: 2.4
Name: snapvision
Version: 0.1.0
Summary: A cross-platform, local-only vision assistant with OCR and AI analysis
Author: SnapVision
License: MIT
Project-URL: Homepage, https://github.com/snapvision/snapvision
Project-URL: Documentation, https://github.com/snapvision/snapvision#readme
Project-URL: Repository, https://github.com/snapvision/snapvision
Project-URL: Issues, https://github.com/snapvision/snapvision/issues
Keywords: ocr,vision,screenshot,llm,cli,cross-platform,ai
Classifier: Development Status :: 3 - Alpha
Classifier: Environment :: Console
Classifier: Intended Audience :: Developers
Classifier: License :: OSI Approved :: MIT License
Classifier: Operating System :: Microsoft :: Windows
Classifier: Operating System :: POSIX :: Linux
Classifier: Operating System :: MacOS
Classifier: Programming Language :: Python :: 3
Classifier: Programming Language :: Python :: 3.10
Classifier: Programming Language :: Python :: 3.11
Classifier: Programming Language :: Python :: 3.12
Classifier: Topic :: Utilities
Requires-Python: >=3.10
Requires-Dist: pynput>=1.7.6
Requires-Dist: PySide6>=6.5.0
Requires-Dist: mss>=9.0.0
Requires-Dist: google-cloud-vision>=3.4.0
Requires-Dist: pillow>=10.0.0
Requires-Dist: groq>=0.4.0
Requires-Dist: openai>=1.0.0
Provides-Extra: dev
Requires-Dist: pytest>=7.0; extra == "dev"
Requires-Dist: pytest-cov>=4.0; extra == "dev"
Requires-Dist: black>=23.0; extra == "dev"
Requires-Dist: mypy>=1.0; extra == "dev"
